{
  "schemaVersion": 1,
  "id": "iw2thshortbows",
  "version": "1.1.1",
  "name": "IWant2TryHard's Shortbows",
  "description": "A mod that adds, well, shortbows! Shoot your foes with high speed! (And in style. Sort of.)",
  "authors": [
    "ThadDev (IWant2TryHard)"
  ],
  "contact": {
    "homepage": "https://thaddev.com/",
    "sources": "https://github.com/MyNameTsThad/CoolIdeasMod/tree/fabric-119"
  },
  "license": "MIT",
  "icon": "assets/iw2thshortbows/icon.png",
  "environment": "*",
  "entrypoints": {
    "main": [
      "com.thaddev.iw2thshortbows.IWant2TryHardsShortbows"
    ],
    "client": [
      "com.thaddev.iw2thshortbows.IWant2TryHardsShortbowsClient"
    ],
    "mm:early_risers": [
      "com.thaddev.iw2thshortbows.asm.FabricASMEarlyRiser"
    ]
  },
  "mixins": [
    "iw2thshortbows.mixins.json"
  ],
  "accesswidener": "iw2thshortbows.accesswidener",

  "depends": {
    "fabricloader": ">=0.14.6",
    "fabric": "*",
    "minecraft": "~1.18.2",
    "java": ">=17",
    "mm": ">=2.3"
  },
  "suggests": {
    "another-mod": "*"
  }
}
